piccione/__init__.py
piccione/download/__init__.py
piccione/download/from_figshare.py
piccione/download/from_sharepoint.py
piccione/upload/__init__.py
piccione/upload/cache_manager.py
piccione/upload/on_figshare.py
piccione/upload/on_internet_archive.py
piccione/upload/on_triplestore.py
piccione/upload/on_zenodo.py
piccione-2.2.0.dist-info/METADATA
piccione-2.2.0.dist-info/WHEEL
piccione-2.2.0.dist-info/licenses/LICENSE.md
piccione-2.2.0.dist-info/RECORD
