Metadata-Version: 2.4
Name: piccione
Version: 2.2.0
Summary: A Python toolkit for uploading and downloading data to external repositories and cloud services.
Project-URL: Homepage, https://github.com/opencitations/piccione
Project-URL: Documentation, https://opencitations.github.io/piccione/
Project-URL: Repository, https://github.com/opencitations/piccione
Author-email: Arcangelo Massari <arcangelo.massari@unibo.it>
License: ISC
License-File: LICENSE.md
Classifier: Development Status :: 3 - Alpha
Classifier: Intended Audience :: Developers
Classifier: License :: OSI Approved :: ISC License (ISCL)
Classifier: Programming Language :: Python :: 3
Classifier: Programming Language :: Python :: 3.10
Classifier: Programming Language :: Python :: 3.11
Classifier: Programming Language :: Python :: 3.12
Classifier: Programming Language :: Python :: 3.13
Requires-Python: >=3.10
Requires-Dist: httpx>=0.28.1
Requires-Dist: internetarchive>=5.7.1
Requires-Dist: pyyaml>=6.0.3
Requires-Dist: redis>=4.5.5
Requires-Dist: requests>=2.32.5
Requires-Dist: rich>=14.2.0
Requires-Dist: sparqlite>=1.0.0
Requires-Dist: tqdm>=4.67.1
